supercommit/__init__.py
supercommit/echo.py
supercommit/executor.py
supercommit/index.py
supercommit-0.1.7.dist-info/METADATA
supercommit-0.1.7.dist-info/RECORD
supercommit-0.1.7.dist-info/WHEEL
supercommit-0.1.7.dist-info/entry_points.txt
supercommit-0.1.7.dist-info/top_level.txt
